{
  "$schema": "https://developer.microsoft.com/json-schemas/fabric/item/report/definition/visualContainer/1.0.0/schema.json",
  "name": "a5a471468a070b9d2ac4",
  "position": {
    "x": 485.88235294117646,
    "y": 431.76470588235293,
    "z": 16000,
    "width": 400,
    "height": 276.47058823529414,
    "tabOrder": 11000
  },
  "visual": {
    "visualType": "shapeMap",
    "query": {
      "queryState": {
        "Category": {
          "projections": [
            {
              "field": {
                "Column": {
                  "Expression": {
                    "SourceRef": {
                      "Entity": "Orders"
                    }
                  },
                  "Property": "State"
                }
              },
              "queryRef": "Orders.State",
              "nativeQueryRef": "State"
            }
          ]
        },
        "Value": {
          "projections": [
            {
              "field": {
                "Aggregation": {
                  "Expression": {
                    "Column": {
                      "Expression": {
                        "SourceRef": {
                          "Entity": "Orders"
                        }
                      },
                      "Property": "Profit"
                    }
                  },
                  "Function": 0
                }
              },
              "queryRef": "Sum(Orders.Profit)",
              "nativeQueryRef": "Sum of Profit"
            }
          ]
        }
      }
    },
    "objects": {
      "shape": [
        {
          "properties": {
            "map": {
              "geoJson": {
                "type": {
                  "expr": {
                    "Literal": {
                      "Value": "'shared'"
                    }
                  }
                },
                "name": {
                  "expr": {
                    "Literal": {
                      "Value": "'usa.states.topo'"
                    }
                  }
                },
                "content": {
                  "expr": {
                    "ResourcePackageItem": {
                      "PackageName": "SharedResources",
                      "PackageType": 2,
                      "ItemName": "usa.states.topo"
                    }
                  }
                }
              }
            },
            "projectionEnum": {
              "expr": {
                "Literal": {
                  "Value": "'albersUsa'"
                }
              }
            }
          }
        }
      ],
      "dataPoint": [
        {
          "properties": {
            "fillRule": {
              "linearGradient2": {
                "min": {
                  "color": {
                    "expr": {
                      "Literal": {
                        "Value": "'#a0d1ff'"
                      }
                    }
                  }
                },
                "max": {
                  "color": {
                    "expr": {
                      "Literal": {
                        "Value": "'#094780'"
                      }
                    }
                  }
                },
                "nullColoringStrategy": {
                  "strategy": {
                    "expr": {
                      "Literal": {
                        "Value": "'asZero'"
                      }
                    }
                  }
                }
              }
            }
          }
        }
      ],
      "zoom": [
        {
          "properties": {
            "selectionZoom": {
              "expr": {
                "Literal": {
                  "Value": "true"
                }
              }
            },
            "autoZoom": {
              "expr": {
                "Literal": {
                  "Value": "true"
                }
              }
            }
          }
        }
      ]
    },
    "visualContainerObjects": {
      "background": [
        {
          "properties": {
            "color": {
              "solid": {
                "color": {
                  "expr": {
                    "ThemeDataColor": {
                      "ColorId": 1,
                      "Percent": 0.4
                    }
                  }
                }
              }
            }
          }
        }
      ],
      "title": [
        {
          "properties": {
            "fontColor": {
              "solid": {
                "color": {
                  "expr": {
                    "ThemeDataColor": {
                      "ColorId": 0,
                      "Percent": 0
                    }
                  }
                }
              }
            },
            "text": {
              "expr": {
                "Literal": {
                  "Value": "'Profit by State'"
                }
              }
            }
          }
        }
      ]
    },
    "drillFilterOtherVisuals": true
  }
}